[
    {
        "kode_bps": "1116010",
        "nama_bps": "TEUNOM",
        "kode_dagri": "11.14.01",
        "nama_dagri": "TEUNOM"
    },
    {
        "kode_bps": "1116011",
        "nama_bps": "PASIE RAYA",
        "kode_dagri": "11.14.09",
        "nama_dagri": "PASIE RAYA"
    },
    {
        "kode_bps": "1116020",
        "nama_bps": "PANGA",
        "kode_dagri": "11.14.06",
        "nama_dagri": "PANGA"
    },
    {
        "kode_bps": "1116030",
        "nama_bps": "KRUENG SABEE",
        "kode_dagri": "11.14.02",
        "nama_dagri": "KRUENG SABEE"
    },
    {
        "kode_bps": "1116040",
        "nama_bps": "SETIA BAKTI",
        "kode_dagri": "11.14.03",
        "nama_dagri": "SETIA BAKTI"
    },
    {
        "kode_bps": "1116050",
        "nama_bps": "SAMPOINIET",
        "kode_dagri": "11.14.04",
        "nama_dagri": "SAMPOI NIET"
    },
    {
        "kode_bps": "1116051",
        "nama_bps": "DARUL HIKMAH",
        "kode_dagri": "11.14.08",
        "nama_dagri": "DARUL HIKMAH"
    },
    {
        "kode_bps": "1116060",
        "nama_bps": "JAYA",
        "kode_dagri": "11.14.05",
        "nama_dagri": "JAYA"
    },
    {
        "kode_bps": "1116061",
        "nama_bps": "INDRA JAYA",
        "kode_dagri": "11.14.07",
        "nama_dagri": "INDRA JAYA"
    }
]