[
    {
        "kode_bps": "3203010",
        "nama_bps": "AGRABINTA",
        "kode_dagri": "32.03.22",
        "nama_dagri": "AGRABINTA"
    },
    {
        "kode_bps": "3203011",
        "nama_bps": "LELES",
        "kode_dagri": "32.03.30",
        "nama_dagri": "LELES"
    },
    {
        "kode_bps": "3203020",
        "nama_bps": "SINDANGBARANG",
        "kode_dagri": "32.03.21",
        "nama_dagri": "SINDANGBARANG"
    },
    {
        "kode_bps": "3203030",
        "nama_bps": "CIDAUN",
        "kode_dagri": "32.03.23",
        "nama_dagri": "CIDAUN"
    },
    {
        "kode_bps": "3203040",
        "nama_bps": "NARINGGUL",
        "kode_dagri": "32.03.24",
        "nama_dagri": "NARINGGUL"
    },
    {
        "kode_bps": "3203050",
        "nama_bps": "CIBINONG",
        "kode_dagri": "32.03.20",
        "nama_dagri": "CUBINONG"
    },
    {
        "kode_bps": "3203051",
        "nama_bps": "CIKADU",
        "kode_dagri": "32.03.26",
        "nama_dagri": "CIKADU"
    },
    {
        "kode_bps": "3203060",
        "nama_bps": "TANGGEUNG",
        "kode_dagri": "32.03.19",
        "nama_dagri": "TANGGEUNG"
    },
    {
        "kode_bps": "3203061",
        "nama_bps": "PASIRKUDA",
        "kode_dagri": "32.03.32",
        "nama_dagri": "PASIRKUDA"
    },
    {
        "kode_bps": "3203070",
        "nama_bps": "KADUPANDAK",
        "kode_dagri": "32.03.17",
        "nama_dagri": "KADUPANDAK"
    },
    {
        "kode_bps": "3203071",
        "nama_bps": "CIJATI",
        "kode_dagri": "32.03.29",
        "nama_dagri": "CIJATI"
    },
    {
        "kode_bps": "3203080",
        "nama_bps": "TAKOKAK",
        "kode_dagri": "32.03.16",
        "nama_dagri": "TAKOKAK"
    },
    {
        "kode_bps": "3203090",
        "nama_bps": "SUKANAGARA",
        "kode_dagri": "32.03.14",
        "nama_dagri": "SUKANAGARA"
    },
    {
        "kode_bps": "3203100",
        "nama_bps": "PAGELARAN",
        "kode_dagri": "32.03.18",
        "nama_dagri": "PAGELARANG"
    },
    {
        "kode_bps": "3203110",
        "nama_bps": "CAMPAKA",
        "kode_dagri": "32.03.15",
        "nama_dagri": "CAMPAKA"
    },
    {
        "kode_bps": "3203111",
        "nama_bps": "CAMPAKAMULYA",
        "kode_dagri": "32.03.25",
        "nama_dagri": "CAMPAKAMULYA"
    },
    {
        "kode_bps": "3203120",
        "nama_bps": "CIBEBER",
        "kode_dagri": "32.03.03",
        "nama_dagri": "CIBEBER"
    },
    {
        "kode_bps": "3203130",
        "nama_bps": "WARUNGKONDANG",
        "kode_dagri": "32.03.02",
        "nama_dagri": "WARUNGKONDANG"
    },
    {
        "kode_bps": "3203131",
        "nama_bps": "GEKBRONG",
        "kode_dagri": "32.03.27",
        "nama_dagri": "GEKBRONG"
    },
    {
        "kode_bps": "3203140",
        "nama_bps": "CILAKU",
        "kode_dagri": "32.03.04",
        "nama_dagri": "CILAKU"
    },
    {
        "kode_bps": "3203150",
        "nama_bps": "SUKALUYU",
        "kode_dagri": "32.03.09",
        "nama_dagri": "SUKALUYU"
    },
    {
        "kode_bps": "3203160",
        "nama_bps": "BOJONGPICUNG",
        "kode_dagri": "32.03.06",
        "nama_dagri": "BONJOGPICUNG"
    },
    {
        "kode_bps": "3203161",
        "nama_bps": "HAURWANGI",
        "kode_dagri": "32.03.31",
        "nama_dagri": "HAURWANGI"
    },
    {
        "kode_bps": "3203170",
        "nama_bps": "CIRANJANG",
        "kode_dagri": "32.03.05",
        "nama_dagri": "CIRANJANG"
    },
    {
        "kode_bps": "3203180",
        "nama_bps": "MANDE",
        "kode_dagri": "32.03.08",
        "nama_dagri": "MANDE"
    },
    {
        "kode_bps": "3203190",
        "nama_bps": "KARANGTENGAH",
        "kode_dagri": "32.03.07",
        "nama_dagri": "KARANGTENGAH"
    },
    {
        "kode_bps": "3203200",
        "nama_bps": "CIANJUR",
        "kode_dagri": "32.03.01",
        "nama_dagri": "CIANJUR"
    },
    {
        "kode_bps": "3203210",
        "nama_bps": "CUGENANG",
        "kode_dagri": "32.03.11",
        "nama_dagri": "CUGENANG"
    },
    {
        "kode_bps": "3203220",
        "nama_bps": "PACET",
        "kode_dagri": "32.03.10",
        "nama_dagri": "PACET"
    },
    {
        "kode_bps": "3203221",
        "nama_bps": "CIPANAS",
        "kode_dagri": "32.03.28",
        "nama_dagri": "CIPANAS"
    },
    {
        "kode_bps": "3203230",
        "nama_bps": "SUKARESMI",
        "kode_dagri": "32.03.13",
        "nama_dagri": "SUKARESMI"
    },
    {
        "kode_bps": "3203240",
        "nama_bps": "CIKALONGKULON",
        "kode_dagri": "32.03.12",
        "nama_dagri": "CIKALONGKULON"
    }
]