[
    {
        "kode_bps": "3214010",
        "nama_bps": "JATILUHUR",
        "kode_dagri": "32.14.03",
        "nama_dagri": "JATILUHUR"
    },
    {
        "kode_bps": "3214011",
        "nama_bps": "SUKASARI",
        "kode_dagri": "32.14.15",
        "nama_dagri": "SUKASARI"
    },
    {
        "kode_bps": "3214020",
        "nama_bps": "MANIIS",
        "kode_dagri": "32.14.07",
        "nama_dagri": "MANIIS"
    },
    {
        "kode_bps": "3214030",
        "nama_bps": "TEGALWARU",
        "kode_dagri": "32.14.08",
        "nama_dagri": "TEGALWARU"
    },
    {
        "kode_bps": "3214040",
        "nama_bps": "PLERED",
        "kode_dagri": "32.14.04",
        "nama_dagri": "PLERED"
    },
    {
        "kode_bps": "3214050",
        "nama_bps": "SUKATANI",
        "kode_dagri": "32.14.05",
        "nama_dagri": "SUKATANI"
    },
    {
        "kode_bps": "3214060",
        "nama_bps": "DARANGDAN",
        "kode_dagri": "32.14.06",
        "nama_dagri": "DARANGDAN"
    },
    {
        "kode_bps": "3214070",
        "nama_bps": "BOJONG",
        "kode_dagri": "32.14.11",
        "nama_dagri": "BOJONG"
    },
    {
        "kode_bps": "3214080",
        "nama_bps": "WANAYASA",
        "kode_dagri": "32.14.09",
        "nama_dagri": "WANAYASA"
    },
    {
        "kode_bps": "3214081",
        "nama_bps": "KIARAPEDES",
        "kode_dagri": "32.14.17",
        "nama_dagri": "KIARAPEDES"
    },
    {
        "kode_bps": "3214090",
        "nama_bps": "PASAWAHAN",
        "kode_dagri": "32.14.10",
        "nama_dagri": "PASAWAHAN"
    },
    {
        "kode_bps": "3214091",
        "nama_bps": "PONDOKSALAM",
        "kode_dagri": "32.14.16",
        "nama_dagri": "PONDOKSALAM"
    },
    {
        "kode_bps": "3214100",
        "nama_bps": "PURWAKARTA",
        "kode_dagri": "32.14.01",
        "nama_dagri": "PURWAKARTA"
    },
    {
        "kode_bps": "3214101",
        "nama_bps": "BABAKANCIKAO",
        "kode_dagri": "32.14.12",
        "nama_dagri": "BABAKANCIKAO"
    },
    {
        "kode_bps": "3214110",
        "nama_bps": "CAMPAKA",
        "kode_dagri": "32.14.02",
        "nama_dagri": "CAMPAKA"
    },
    {
        "kode_bps": "3214111",
        "nama_bps": "CIBATU",
        "kode_dagri": "32.14.14",
        "nama_dagri": "CIBATU"
    },
    {
        "kode_bps": "3214112",
        "nama_bps": "BUNGURSARI",
        "kode_dagri": "32.14.13",
        "nama_dagri": "BUNGURSARI"
    }
]