[
    {
        "kode_bps": "3603010",
        "nama_bps": "CISOKA",
        "kode_dagri": "36.03.05",
        "nama_dagri": "CISOKA"
    },
    {
        "kode_bps": "3603011",
        "nama_bps": "SOLEAR",
        "kode_dagri": "36.03.31",
        "nama_dagri": "SOLEAR"
    },
    {
        "kode_bps": "3603020",
        "nama_bps": "TIGARAKSA",
        "kode_dagri": "36.03.03",
        "nama_dagri": "TIGARAKSA"
    },
    {
        "kode_bps": "3603021",
        "nama_bps": "JAMBE",
        "kode_dagri": "36.03.04",
        "nama_dagri": "JAMBE"
    },
    {
        "kode_bps": "3603030",
        "nama_bps": "CIKUPA",
        "kode_dagri": "36.03.18",
        "nama_dagri": "CIKUPA"
    },
    {
        "kode_bps": "3603040",
        "nama_bps": "PANONGAN",
        "kode_dagri": "36.03.19",
        "nama_dagri": "PANONGAN"
    },
    {
        "kode_bps": "3603050",
        "nama_bps": "CURUG",
        "kode_dagri": "36.03.17",
        "nama_dagri": "CURUG"
    },
    {
        "kode_bps": "3603051",
        "nama_bps": "KELAPA DUA",
        "kode_dagri": "36.03.28",
        "nama_dagri": "KELAPA DUA"
    },
    {
        "kode_bps": "3603060",
        "nama_bps": "LEGOK",
        "kode_dagri": "36.03.20",
        "nama_dagri": "LEGOK"
    },
    {
        "kode_bps": "3603070",
        "nama_bps": "PAGEDANGAN",
        "kode_dagri": "36.03.22",
        "nama_dagri": "PAGEDANGAN"
    },
    {
        "kode_bps": "3603081",
        "nama_bps": "CISAUK",
        "kode_dagri": "36.03.23",
        "nama_dagri": "CISAUK"
    },
    {
        "kode_bps": "3603120",
        "nama_bps": "PASARKEMIS",
        "kode_dagri": "36.03.12",
        "nama_dagri": "PASAR KEMIS"
    },
    {
        "kode_bps": "3603121",
        "nama_bps": "SINDANG JAYA",
        "kode_dagri": "36.03.29",
        "nama_dagri": "SINDANG JAYA"
    },
    {
        "kode_bps": "3603130",
        "nama_bps": "BALARAJA",
        "kode_dagri": "36.03.01",
        "nama_dagri": "BALARAJA"
    },
    {
        "kode_bps": "3603131",
        "nama_bps": "JAYANTI",
        "kode_dagri": "36.03.02",
        "nama_dagri": "JAYANTI"
    },
    {
        "kode_bps": "3603132",
        "nama_bps": "SUKAMULYA",
        "kode_dagri": "36.03.27",
        "nama_dagri": "SUKAMULYA"
    },
    {
        "kode_bps": "3603140",
        "nama_bps": "KRESEK",
        "kode_dagri": "36.03.06",
        "nama_dagri": "KRESEK"
    },
    {
        "kode_bps": "3603141",
        "nama_bps": "GUNUNG KALER",
        "kode_dagri": "36.03.32",
        "nama_dagri": "GUNUNG KALER"
    },
    {
        "kode_bps": "3603150",
        "nama_bps": "KRONJO",
        "kode_dagri": "36.03.07",
        "nama_dagri": "KRONJO"
    },
    {
        "kode_bps": "3603151",
        "nama_bps": "MEKAR BARU",
        "kode_dagri": "36.03.33",
        "nama_dagri": "MEKAR BARU"
    },
    {
        "kode_bps": "3603160",
        "nama_bps": "MAUK",
        "kode_dagri": "36.03.08",
        "nama_dagri": "MAUK"
    },
    {
        "kode_bps": "3603161",
        "nama_bps": "KEMIRI",
        "kode_dagri": "36.03.09",
        "nama_dagri": "KEMIRI"
    },
    {
        "kode_bps": "3603162",
        "nama_bps": "SUKADIRI",
        "kode_dagri": "36.03.10",
        "nama_dagri": "SUKADIRI"
    },
    {
        "kode_bps": "3603170",
        "nama_bps": "RAJEG",
        "kode_dagri": "36.03.11",
        "nama_dagri": "RAJEG"
    },
    {
        "kode_bps": "3603180",
        "nama_bps": "SEPATAN",
        "kode_dagri": "36.03.16",
        "nama_dagri": "SEPATAN"
    },
    {
        "kode_bps": "3603181",
        "nama_bps": "SEPATAN TIMUR",
        "kode_dagri": "36.03.30",
        "nama_dagri": "SEPATAN TIMUR"
    },
    {
        "kode_bps": "3603190",
        "nama_bps": "PAKUHAJI",
        "kode_dagri": "36.03.15",
        "nama_dagri": "PAKUHAJI"
    },
    {
        "kode_bps": "3603200",
        "nama_bps": "TELUKNAGA",
        "kode_dagri": "36.03.13",
        "nama_dagri": "TELUKNAGA"
    },
    {
        "kode_bps": "3603210",
        "nama_bps": "KOSAMBI",
        "kode_dagri": "36.03.14",
        "nama_dagri": "KOSAMBI"
    }
]