[
    {
        "kode_bps": "6504010",
        "nama_bps": "KRAYAN SELATAN",
        "kode_dagri": "65.03.07",
        "nama_dagri": "KRAYAN SELATAN"
    },
    {
        "kode_bps": "6504011",
        "nama_bps": "KRAYAN TENGAH",
        "kode_dagri": "65.03.17",
        "nama_dagri": "KRAYAN TENGAH"
    },
    {
        "kode_bps": "6504020",
        "nama_bps": "KRAYAN",
        "kode_dagri": "65.03.05",
        "nama_dagri": "KRAYAN"
    },
    {
        "kode_bps": "6504021",
        "nama_bps": "KRAYAN TIMUR",
        "kode_dagri": "65.03.18",
        "nama_dagri": "KRAYAN TIMUR"
    },
    {
        "kode_bps": "6504022",
        "nama_bps": "KRAYAN BARAT",
        "kode_dagri": "65.03.19",
        "nama_dagri": "KRAYAN BARAT"
    },
    {
        "kode_bps": "6504030",
        "nama_bps": "LUMBIS OGONG",
        "kode_dagri": "65.03.15",
        "nama_dagri": "LUMBIS OGONG"
    },
    {
        "kode_bps": "6504031",
        "nama_bps": "LUMBIS PANSIANGAN",
        "kode_dagri": "65.03.20",
        "nama_dagri": "LUMBIS PANSIANGAN"
    },
    {
        "kode_bps": "6504032",
        "nama_bps": "LUMBIS HULU",
        "kode_dagri": "65.03.21",
        "nama_dagri": "LUMBIS HULU"
    },
    {
        "kode_bps": "6504040",
        "nama_bps": "LUMBIS",
        "kode_dagri": "65.03.04",
        "nama_dagri": "LUMBIS"
    },
    {
        "kode_bps": "6504050",
        "nama_bps": "SEMBAKUNG ATULAI",
        "kode_dagri": "65.03.16",
        "nama_dagri": "SEMBAKUNG ATULAI"
    },
    {
        "kode_bps": "6504060",
        "nama_bps": "SEMBAKUNG",
        "kode_dagri": "65.03.03",
        "nama_dagri": "SEMBAKUNG"
    },
    {
        "kode_bps": "6504070",
        "nama_bps": "SEBUKU",
        "kode_dagri": "65.03.06",
        "nama_dagri": "SEBUKU"
    },
    {
        "kode_bps": "6504080",
        "nama_bps": "TULIN ONSOI",
        "kode_dagri": "65.03.14",
        "nama_dagri": "TULIN ONSOI"
    },
    {
        "kode_bps": "6504090",
        "nama_bps": "SEI MENGGARIS",
        "kode_dagri": "65.03.13",
        "nama_dagri": "SEI MENGGARIS"
    },
    {
        "kode_bps": "6504100",
        "nama_bps": "NUNUKAN",
        "kode_dagri": "65.03.02",
        "nama_dagri": "NUNUKAN"
    },
    {
        "kode_bps": "6504110",
        "nama_bps": "NUNUKAN SELATAN",
        "kode_dagri": "65.03.09",
        "nama_dagri": "NUNUKAN SELATAN"
    },
    {
        "kode_bps": "6504120",
        "nama_bps": "SEBATIK BARAT",
        "kode_dagri": "65.03.08",
        "nama_dagri": "SEBATIK BARAT"
    },
    {
        "kode_bps": "6504130",
        "nama_bps": "SEBATIK",
        "kode_dagri": "65.03.01",
        "nama_dagri": "SEBATIK"
    },
    {
        "kode_bps": "6504140",
        "nama_bps": "SEBATIK TIMUR",
        "kode_dagri": "65.03.10",
        "nama_dagri": "SEBATIK TIMUR"
    },
    {
        "kode_bps": "6504150",
        "nama_bps": "SEBATIK TENGAH",
        "kode_dagri": "65.03.12",
        "nama_dagri": "SEBATIK TENGAH"
    },
    {
        "kode_bps": "6504160",
        "nama_bps": "SEBATIK UTARA",
        "kode_dagri": "65.03.11",
        "nama_dagri": "SEBATIK UTARA"
    }
]