[
    {
        "kode_bps": "7305010",
        "nama_bps": "MANGARABOMBANG",
        "kode_dagri": "73.05.02",
        "nama_dagri": "MANGARABOMBANG"
    },
    {
        "kode_bps": "7305011",
        "nama_bps": "LAIKANG",
        "kode_dagri": "73.05.12",
        "nama_dagri": "LAIKANG"
    },
    {
        "kode_bps": "7305020",
        "nama_bps": "MAPPAKASUNGGU",
        "kode_dagri": "73.05.01",
        "nama_dagri": "MAPPAKASUNGGU"
    },
    {
        "kode_bps": "7305021",
        "nama_bps": "SANROBONE",
        "kode_dagri": "73.05.08",
        "nama_dagri": "SANROBONE"
    },
    {
        "kode_bps": "7305022",
        "nama_bps": "KEPULAUAN TANAKEKE",
        "kode_dagri": "73.05.10",
        "nama_dagri": "KEPULAUAN TANAKEKE"
    },
    {
        "kode_bps": "7305030",
        "nama_bps": "POLONGBANGKENG SELATAN",
        "kode_dagri": "73.05.03",
        "nama_dagri": "POLONGBANGKENG SELATAN"
    },
    {
        "kode_bps": "7305031",
        "nama_bps": "PATTALLASSANG",
        "kode_dagri": "73.05.07",
        "nama_dagri": "PATTALLASSANG"
    },
    {
        "kode_bps": "7305040",
        "nama_bps": "POLONGBANGKENG UTARA",
        "kode_dagri": "73.05.04",
        "nama_dagri": "POLONGBANGKENG UTARA"
    },
    {
        "kode_bps": "7305041",
        "nama_bps": "POLONGBANGKENG TIMUR",
        "kode_dagri": "73.05.11",
        "nama_dagri": "POLONGBANGKENG TIMUR"
    },
    {
        "kode_bps": "7305050",
        "nama_bps": "GALESONG SELATAN",
        "kode_dagri": "73.05.05",
        "nama_dagri": "GALESONG SELATAN"
    },
    {
        "kode_bps": "7305051",
        "nama_bps": "GALESONG",
        "kode_dagri": "73.05.09",
        "nama_dagri": "GALESONG"
    },
    {
        "kode_bps": "7305060",
        "nama_bps": "GALESONG UTARA",
        "kode_dagri": "73.05.06",
        "nama_dagri": "GALESONG UTARA"
    }
]