[
    {
        "kode_bps": "7309010",
        "nama_bps": "LIUKANG TANGAYA",
        "kode_dagri": "73.10.01",
        "nama_dagri": "LIUKANG TANGAYA"
    },
    {
        "kode_bps": "7309020",
        "nama_bps": "LIUKANG KALMAS",
        "kode_dagri": "73.10.02",
        "nama_dagri": "LIUKANG KALMAS"
    },
    {
        "kode_bps": "7309030",
        "nama_bps": "LIUKANG TUPABBIRING",
        "kode_dagri": "73.10.03",
        "nama_dagri": "LIUKANG TUPABBIRING"
    },
    {
        "kode_bps": "7309031",
        "nama_bps": "LIUKANG TUPABBIRING UTARA",
        "kode_dagri": "73.10.13",
        "nama_dagri": "LIUKANG TUPABBIRING UTARA"
    },
    {
        "kode_bps": "7309040",
        "nama_bps": "PANGKAJENE",
        "kode_dagri": "73.10.04",
        "nama_dagri": "PANGKAJENE"
    },
    {
        "kode_bps": "7309041",
        "nama_bps": "MINASATENE",
        "kode_dagri": "73.10.10",
        "nama_dagri": "MINASATE'NE"
    },
    {
        "kode_bps": "7309050",
        "nama_bps": "BALOCCI",
        "kode_dagri": "73.10.05",
        "nama_dagri": "BALOCCI"
    },
    {
        "kode_bps": "7309051",
        "nama_bps": "TONDONG TALLASA",
        "kode_dagri": "73.10.12",
        "nama_dagri": "TONDONG TALLASA"
    },
    {
        "kode_bps": "7309060",
        "nama_bps": "BUNGORO",
        "kode_dagri": "73.10.06",
        "nama_dagri": "BUNGORO"
    },
    {
        "kode_bps": "7309070",
        "nama_bps": "LABAKKANG",
        "kode_dagri": "73.10.07",
        "nama_dagri": "LABAKKANG"
    },
    {
        "kode_bps": "7309080",
        "nama_bps": "MA'RANG",
        "kode_dagri": "73.10.08",
        "nama_dagri": "MARANG"
    },
    {
        "kode_bps": "7309091",
        "nama_bps": "SEGERI",
        "kode_dagri": "73.10.09",
        "nama_dagri": "SEGERI"
    },
    {
        "kode_bps": "7309092",
        "nama_bps": "MANDALLE",
        "kode_dagri": "73.10.11",
        "nama_dagri": "MANDALLE"
    }
]