[
    {
        "kode_bps": "7314010",
        "nama_bps": "PANCA LAUTANG",
        "kode_dagri": "73.14.01",
        "nama_dagri": "PANCA LAUTANG"
    },
    {
        "kode_bps": "7314020",
        "nama_bps": "TELLULIMPO E",
        "kode_dagri": "73.14.02",
        "nama_dagri": "TELLU LIMPOE"
    },
    {
        "kode_bps": "7314030",
        "nama_bps": "WATANG PULU",
        "kode_dagri": "73.14.03",
        "nama_dagri": "WATANG PULU"
    },
    {
        "kode_bps": "7314040",
        "nama_bps": "BARANTI",
        "kode_dagri": "73.14.04",
        "nama_dagri": "BARANTI"
    },
    {
        "kode_bps": "7314050",
        "nama_bps": "PANCA RIJANG",
        "kode_dagri": "73.14.05",
        "nama_dagri": "PANCA RIJANG"
    },
    {
        "kode_bps": "7314051",
        "nama_bps": "KULO",
        "kode_dagri": "73.14.06",
        "nama_dagri": "KULO"
    },
    {
        "kode_bps": "7314060",
        "nama_bps": "MARITENGNGAE",
        "kode_dagri": "73.14.07",
        "nama_dagri": "MARITENGNGAE"
    },
    {
        "kode_bps": "7314061",
        "nama_bps": "WATANG SIDENRENG",
        "kode_dagri": "73.14.08",
        "nama_dagri": "WATANG SIDENRENG"
    },
    {
        "kode_bps": "7314070",
        "nama_bps": "PITU RIAWA",
        "kode_dagri": "73.14.10",
        "nama_dagri": "PITU RIAWA"
    },
    {
        "kode_bps": "7314080",
        "nama_bps": "DUAPITUE",
        "kode_dagri": "73.14.09",
        "nama_dagri": "DUA PITUE"
    },
    {
        "kode_bps": "7314081",
        "nama_bps": "PITU RIASE",
        "kode_dagri": "73.14.11",
        "nama_dagri": "PITU RIASE"
    }
]