[
    {
        "kode_bps": "7413010",
        "nama_bps": "TIWORO KEPULAUAN",
        "kode_dagri": "74.13.09",
        "nama_dagri": "TIWORO KEPULAUAN"
    },
    {
        "kode_bps": "7413020",
        "nama_bps": "MAGINTI",
        "kode_dagri": "74.13.06",
        "nama_dagri": "MAGINTI"
    },
    {
        "kode_bps": "7413030",
        "nama_bps": "TIWORO TENGAH",
        "kode_dagri": "74.13.07",
        "nama_dagri": "TIWORO TENGAH"
    },
    {
        "kode_bps": "7413040",
        "nama_bps": "TIWORO SELATAN",
        "kode_dagri": "74.13.05",
        "nama_dagri": "TIWORO SELATAN"
    },
    {
        "kode_bps": "7413050",
        "nama_bps": "TIWORO UTARA",
        "kode_dagri": "74.13.08",
        "nama_dagri": "TIWORO UTARA"
    },
    {
        "kode_bps": "7413060",
        "nama_bps": "LAWA",
        "kode_dagri": "74.13.03",
        "nama_dagri": "LAWA"
    },
    {
        "kode_bps": "7413070",
        "nama_bps": "SAWERIGADI",
        "kode_dagri": "74.13.01",
        "nama_dagri": "SAWERIGADI"
    },
    {
        "kode_bps": "7413080",
        "nama_bps": "BARANGKA",
        "kode_dagri": "74.13.02",
        "nama_dagri": "BARANGKA"
    },
    {
        "kode_bps": "7413090",
        "nama_bps": "WA DAGA",
        "kode_dagri": "74.13.04",
        "nama_dagri": "WADAGA"
    },
    {
        "kode_bps": "7413100",
        "nama_bps": "KUSAMBI",
        "kode_dagri": "74.13.10",
        "nama_dagri": "KUSAMBI"
    },
    {
        "kode_bps": "7413110",
        "nama_bps": "NAPANO KUSAMBI",
        "kode_dagri": "74.13.11",
        "nama_dagri": "NAPANO KUSAMBI"
    }
]